money/__init__.py
money/exceptions.py
money/exchange.py
money/money.py
money/tests/__init__.py
money/tests/mixins.py
money/tests/test_docs.py
money/tests/test_exchange.py
money/tests/test_money.py
money/tests/test_xmoney.py
money_py3-2.0.0.dist-info/LICENSE
money_py3-2.0.0.dist-info/METADATA
money_py3-2.0.0.dist-info/WHEEL
money_py3-2.0.0.dist-info/RECORD
