Metadata-Version: 2.3
Name: money-py3
Version: 2.0.0
Summary: Modern Python 3.9+ Money Class with Currency Exchange
License: MIT
Keywords: money,currency,exchange,decimal,financial
Author: Carlos Palol
Author-email: carlos.palol@awarepixel.com
Maintainer: Fever
Maintainer-email: engineering@feverup.com
Requires-Python: >=3.9
Classifier: Development Status :: 5 - Production/Stable
Classifier: Intended Audience :: Developers
Classifier: License :: OSI Approved :: MIT License
Classifier: Programming Language :: Python :: 3
Classifier: Programming Language :: Python :: 3.9
Classifier: Programming Language :: Python :: 3.10
Classifier: Programming Language :: Python :: 3.11
Classifier: Programming Language :: Python :: 3.12
Classifier: Programming Language :: Python :: 3 :: Only
Classifier: Topic :: Software Development :: Libraries :: Python Modules
Classifier: Topic :: Office/Business :: Financial
Classifier: Topic :: Scientific/Engineering :: Mathematics
Classifier: Operating System :: OS Independent
Provides-Extra: formatting
Requires-Dist: babel (>=2.15,<2.18) ; extra == "formatting"
Requires-Dist: packaging (>=20.0)
Project-URL: Bug Reports, https://github.com/Feverup/money-py3/issues
Project-URL: Documentation, https://github.com/Feverup/money-py3#readme
Project-URL: Homepage, https://github.com/Feverup/money-py3
Project-URL: Original Project, https://github.com/carlospalol/money
Project-URL: Repository, https://github.com/Feverup/money-py3
Project-URL: Source, https://github.com/Feverup/money-py3
